toutsurmoneau/__init__.py
toutsurmoneau/__main__.py
toutsurmoneau/async_client.py
toutsurmoneau/client.py
toutsurmoneau/const.py
toutsurmoneau/errors.py
toutsurmoneau-0.0.27.dist-info/LICENSE
toutsurmoneau-0.0.27.dist-info/METADATA
toutsurmoneau-0.0.27.dist-info/WHEEL
toutsurmoneau-0.0.27.dist-info/entry_points.txt
toutsurmoneau-0.0.27.dist-info/top_level.txt
toutsurmoneau-0.0.27.dist-info/RECORD
