Metadata-Version: 2.2
Name: toutsurmoneau
Version: 0.0.27
Summary: Retrieve water meter information from Suez web site https://www.toutsurmoneau.fr/ and other water providers in france.
Author-email: Laurent MARTIN <laurent.martin.l@gmail.com>
Maintainer-email: Laurent MARTIN <laurent.martin.l@gmail.com>
License:                                  Apache License
Project-URL: Homepage, https://github.com/laurent-martin/py-mon-eau
Project-URL: Bug Tracker, https://github.com/laurent-martin/py-mon-eau/issues
Keywords: suez,toutsurmoneau
Classifier: Development Status :: 4 - Beta
Classifier: Programming Language :: Python :: 3
Classifier: License :: OSI Approved :: MIT License
Classifier: Operating System :: OS Independent
Requires-Python: >=3.7
License-File: LICENSE
Requires-Dist: aiohttp
Requires-Dist: asyncio
Requires-Dist: pyyaml
Requires-Dist: datetime
